Ofit/__init__.py
Ofit/modulo.py
OFit-0.1.6.dist-info/METADATA
OFit-0.1.6.dist-info/WHEEL
OFit-0.1.6.dist-info/top_level.txt
OFit-0.1.6.dist-info/RECORD
