Metadata-Version: 2.1
Name: OFit
Version: 0.1.6
Summary: Esta libreria se encarga de realizar el analisis de datos usando un kernel gaussiano, trucube y Epanechnikov
Home-page: UNKNOWN
Author: Juan Esteban Ospina 
Author-email: juan.ospina25@udea.edu.co
License: MIT
Platform: UNKNOWN
Requires-Python: >=3.10.12
Requires-Dist: matplotlib (==3.8.0)
Requires-Dist: numpy (==1.26.1)
Requires-Dist: pandas (==2.1.1)
